external/himl/setup.py
external/himl/himl/__init__.py
external/himl/himl/config_generator.py
external/himl/himl/config_merger.py
external/himl/himl/filter_rules.py
external/himl/himl/inject_env.py
external/himl/himl/inject_secrets.py
external/himl/himl/interpolation.py
external/himl/himl/main.py
external/himl/himl/python_compat.py
external/himl/himl/remote_state.py
external/himl/himl/secret_resolvers.py
external/himl/himl/simples3.py
external/himl/himl/simplessm.py
external/himl/himl/simplevault.py
external/himl/tests/test_config_generator.py
external/himl/tests/test_interpolation.py
pigeon_config/__init__.py
pigeon_config/__main__.py
pigeon_config/himl/__init__.py
pigeon_config/himl/config_generator.py
pigeon_config/himl/config_merger.py
pigeon_config/himl/filter_rules.py
pigeon_config/himl/inject_env.py
pigeon_config/himl/inject_secrets.py
pigeon_config/himl/interpolation.py
pigeon_config/himl/main.py
pigeon_config/himl/python_compat.py
pigeon_config/himl/remote_state.py
pigeon_config/himl/secret_resolvers.py
pigeon_config/himl/simples3.py
pigeon_config/himl/simplessm.py
pigeon_config/himl/simplevault.py
pigeon_config-0.2.3.dist-info/licenses/LICENSE
pigeon_config-0.2.3.dist-info/METADATA
pigeon_config-0.2.3.dist-info/WHEEL
pigeon_config-0.2.3.dist-info/entry_points.txt
pigeon_config-0.2.3.dist-info/top_level.txt
pigeon_config-0.2.3.dist-info/RECORD
