Metadata-Version: 2.4
Name: pigeon-config
Version: 0.2.3
Summary: A tool for managing multiple configuration files. Based off of Adobe's HIML.
Author-email: Cameron Devine <cameron.devine@alleninstitute.org>
License: BSD 3 Clause
Project-URL: Homepage, https://github.com/AllenInstitute/pigeon-config
Project-URL: Repository, https://github.com/AllenInstitute/pigeon-config
Project-URL: Issues, https://github.com/AllenInstitute/pigeon-config/issues
Classifier: Environment :: Console
Classifier: Intended Audience :: Developers
Classifier: Intended Audience :: Information Technology
Classifier: Intended Audience :: System Administrators
Classifier: License :: OSI Approved :: BSD License
Requires-Python: <3.12,>=3.8
License-File: LICENSE
Requires-Dist: PyYAML
Requires-Dist: deepmerge==1.1.1
Requires-Dist: lru_cache==0.2.3
Requires-Dist: backports.functools_lru_cache==1.6.6
Requires-Dist: pyyaml~=6.0.2
Requires-Dist: boto3~=1.35.94
Requires-Dist: hvac~=2.3.0
Requires-Dist: pathlib2
Dynamic: license-file
